transcribify/__init__.py
transcribify/audio_processing.py
transcribify/gui.py
transcribify/live_transcription.py
transcribify/models.py
transcribify/transcription.py
transcribify/utils.py
transcribify-0.1.1.dist-info/METADATA
transcribify-0.1.1.dist-info/WHEEL
transcribify-0.1.1.dist-info/top_level.txt
transcribify-0.1.1.dist-info/RECORD
