Metadata-Version: 2.1
Name: transcribify
Version: 0.1.1
Summary: A tool for transcribing audio files with optional speaker diarization
Home-page: https://github.com/lukehiura/transcribify
Author: Luke Hiura
Author-email: lhiur001@gmail.com
Classifier: Development Status :: 3 - Alpha
Classifier: Intended Audience :: Developers
Classifier: License :: OSI Approved :: MIT License
Classifier: Operating System :: OS Independent
Classifier: Programming Language :: Python :: 3
Classifier: Programming Language :: Python :: 3.7
Classifier: Programming Language :: Python :: 3.8
Classifier: Programming Language :: Python :: 3.9
Requires-Python: >=3.7
Requires-Dist: torch
Requires-Dist: transformers
Requires-Dist: pyannote.audio
Requires-Dist: pydub
Requires-Dist: PySimpleGUI
Requires-Dist: Jinja2
Requires-Dist: pyaudio
Requires-Dist: numpy
